{
    "experiments_path": "/atlas/u/xuyilun/vctk/experiments_wave_vq_whole",
    "results_path": "/atlas/u/xuyilun/vctk/experiments_wave_vq_whole/results",
    "configuration_path": "../configurations/vctk_deconv.yaml",
    "seed": 1234,
    "experiments": {
        "baseline": {
            "num_epochs": 200,
            "batch_size": 3,
            "num_embeddinos.path.join(root, fname)gs": 44,
            "use_device": "cuda:0",
            "normalize": true,
            "original": false
        }
    }
}

